k_diagram-1.3.5.dist-info/licenses/LICENSE
kdiagram/__init__.py
kdiagram/__main__.py
kdiagram/config.py
kdiagram/decorators.py
kdiagram/metrics.py
kdiagram/api/__init__.py
kdiagram/api/bunch.py
kdiagram/api/summary.py
kdiagram/api/typing.py
kdiagram/api/util.py
kdiagram/cli/__init__.py
kdiagram/cli/_utils.py
kdiagram/cli/plot_anomalies.py
kdiagram/cli/plot_comparison.py
kdiagram/cli/plot_cond_relationship.py
kdiagram/cli/plot_confusion_matrices.py
kdiagram/cli/plot_context_corr.py
kdiagram/cli/plot_context_err.py
kdiagram/cli/plot_coverages.py
kdiagram/cli/plot_credibility.py
kdiagram/cli/plot_drift.py
kdiagram/cli/plot_errors.py
kdiagram/cli/plot_eval_ext.py
kdiagram/cli/plot_eval_performance.py
kdiagram/cli/plot_eval_relationship.py
kdiagram/cli/plot_feature_based.py
kdiagram/cli/plot_fields.py
kdiagram/cli/plot_intervals.py
kdiagram/cli/plot_pr_roc.py
kdiagram/cli/plot_probs.py
kdiagram/cli/plot_reliability.py
kdiagram/cli/plot_sharpness.py
kdiagram/cli/plot_taylord.py
kdiagram/cli/plot_temporal.py
kdiagram/cli/plot_ts_analyses.py
kdiagram/cli/plot_velocities.py
kdiagram/cli/plot_vs.py
kdiagram/compat/__init__.py
kdiagram/compat/matplotlib.py
kdiagram/compat/numpy.py
kdiagram/compat/sklearn.py
kdiagram/core/__init__.py
kdiagram/core/_io_utils.py
kdiagram/core/io.py
kdiagram/core/property.py
kdiagram/datasets/__init__.py
kdiagram/datasets/_property.py
kdiagram/datasets/load.py
kdiagram/datasets/make.py
kdiagram/datasets/data/__init__.py
kdiagram/datasets/data/min_zhongshan.csv
kdiagram/plot/__init__.py
kdiagram/plot/_properties.py
kdiagram/plot/anomaly.py
kdiagram/plot/comparison.py
kdiagram/plot/context.py
kdiagram/plot/errors.py
kdiagram/plot/evaluation.py
kdiagram/plot/feature_based.py
kdiagram/plot/probabilistic.py
kdiagram/plot/relationship.py
kdiagram/plot/taylor_diagram.py
kdiagram/plot/uncertainty.py
kdiagram/utils/__init__.py
kdiagram/utils/_deps.py
kdiagram/utils/deps.py
kdiagram/utils/diagnose_q.py
kdiagram/utils/forecast_utils.py
kdiagram/utils/fs.py
kdiagram/utils/generic_utils.py
k_diagram-1.3.5.dist-info/METADATA
k_diagram-1.3.5.dist-info/WHEEL
k_diagram-1.3.5.dist-info/entry_points.txt
k_diagram-1.3.5.dist-info/top_level.txt
k_diagram-1.3.5.dist-info/RECORD
