Metadata-Version: 2.4
Name: k-diagram
Version: 1.3.5
Summary: Rethinking Forecasting Uncertainty via Polar-Based Visualization
Author-email: Laurent Kouadio <etanoyau@gmail.com>
License: Apache-2.0
Project-URL: Home page, https://k-diagram.readthedocs.io
Project-URL: API Documentation, https://k-diagram.readthedocs.io/en/latest/api_references.html
Project-URL: Installation guide, https://k-diagram.readthedocs.io/en/latest/installation.html
Project-URL: User guide, https://k-diagram.readthedocs.io/en/latest/user_guide.html
Project-URL: Bug Tracker, https://github.com/earth-ai-tech/k-diagram/issues
Project-URL: Source, https://github.com/earth-ai-tech/k-diagram
Keywords: forecasting,uncertainty visualization,model evaluation
Classifier: Development Status :: 4 - Beta
Classifier: Intended Audience :: Science/Research
Classifier: Intended Audience :: Developers
Classifier: Topic :: Software Development
Classifier: Topic :: Scientific/Engineering
Classifier: Programming Language :: Python
Classifier: Programming Language :: Python :: 3.9
Classifier: Programming Language :: Python :: 3.10
Classifier: Programming Language :: Python :: 3.11
Classifier: Programming Language :: Python :: 3.12
Classifier: Programming Language :: Python :: 3.13
Classifier: Operating System :: OS Independent
Classifier: Operating System :: Microsoft :: Windows
Classifier: Operating System :: POSIX
Classifier: Operating System :: Unix
Requires-Python: >=3.9
License-File: LICENSE
Requires-Dist: numpy>=1.22
Requires-Dist: pandas>=1.0
Requires-Dist: scipy>=1.5
Requires-Dist: matplotlib>=3.3
Requires-Dist: seaborn>=0.11
Requires-Dist: scikit-learn>=0.24
Provides-Extra: docs
Requires-Dist: sphinx<8.0,>=7.0; extra == "docs"
Requires-Dist: furo; extra == "docs"
Requires-Dist: sphinx-copybutton; extra == "docs"
Requires-Dist: myst-parser; extra == "docs"
Requires-Dist: sphinx-design; extra == "docs"
Requires-Dist: sphinx-gallery; extra == "docs"
Requires-Dist: sphinxcontrib-jsmath; extra == "docs"
Requires-Dist: sphinx-mathjax-offline; extra == "docs"
Requires-Dist: sphinx-issues; extra == "docs"
Requires-Dist: sphinx-prompt; extra == "docs"
Requires-Dist: sphinxcontrib-bibtex; extra == "docs"
Requires-Dist: numpydoc>=1.6; extra == "docs"
Provides-Extra: dev
Requires-Dist: pytest>=8.0; extra == "dev"
Requires-Dist: pytest-cov>=4.1; extra == "dev"
Requires-Dist: pytest-xdist; extra == "dev"
Requires-Dist: pytest-mock; extra == "dev"
Requires-Dist: black>=24.0; extra == "dev"
Requires-Dist: ruff>=0.4; extra == "dev"
Requires-Dist: coverage[toml]>=7.0; extra == "dev"
Requires-Dist: tqdm; extra == "dev"
Requires-Dist: statsmodels; extra == "dev"
Requires-Dist: requests; extra == "dev"
Dynamic: license-file
